odoo/addons/rma_lot_autocreate/README.rst
odoo/addons/rma_lot_autocreate/__init__.py
odoo/addons/rma_lot_autocreate/__manifest__.py
odoo/addons/rma_lot_autocreate/data/ir_sequence_data.xml
odoo/addons/rma_lot_autocreate/i18n/it.po
odoo/addons/rma_lot_autocreate/i18n/rma_lot_autocreate.pot
odoo/addons/rma_lot_autocreate/models/__init__.py
odoo/addons/rma_lot_autocreate/models/rma.py
odoo/addons/rma_lot_autocreate/models/rma_operation.py
odoo/addons/rma_lot_autocreate/readme/CONFIGURE.md
odoo/addons/rma_lot_autocreate/readme/CONTEXT.md
odoo/addons/rma_lot_autocreate/readme/CONTRIBUTORS.md
odoo/addons/rma_lot_autocreate/readme/DESCRIPTION.md
odoo/addons/rma_lot_autocreate/readme/USAGE.md
odoo/addons/rma_lot_autocreate/static/description/icon.png
odoo/addons/rma_lot_autocreate/static/description/index.html
odoo/addons/rma_lot_autocreate/tests/__init__.py
odoo/addons/rma_lot_autocreate/tests/test_rma_lot_autocreate.py
odoo/addons/rma_lot_autocreate/views/rma_operation.xml
odoo_addon_rma_lot_autocreate-16.0.1.0.0.5.dist-info/METADATA
odoo_addon_rma_lot_autocreate-16.0.1.0.0.5.dist-info/WHEEL
odoo_addon_rma_lot_autocreate-16.0.1.0.0.5.dist-info/top_level.txt
odoo_addon_rma_lot_autocreate-16.0.1.0.0.5.dist-info/RECORD
