Metadata-Version: 2.1
Name: odoo-addon-rma_lot_autocreate
Version: 16.0.1.0.0.5
Summary: Auto-generate stock lot at RMA confirm using per-operation sequence
Home-page: https://github.com/OCA/rma
Author: ACSONE SA/NV,Odoo Community Association (OCA)
Author-email: support@odoo-community.org
License: AGPL-3
Classifier: Programming Language :: Python
Classifier: Framework :: Odoo
Classifier: Framework :: Odoo :: 16.0
Classifier: License :: OSI Approved :: GNU Affero General Public License v3
Requires-Python: >=3.10
Requires-Dist: odoo-addon-rma-lot<16.1dev,>=16.0dev
Requires-Dist: odoo<16.1dev,>=16.0a
